[
  {
    "id": 39249395,
    "name": "HKeLeaveSystem",
    "full_name": "pfizer-commercial/HKeLeaveSystem",
    "clone_url": "https://github.com/pfizer-commercial/HKeLeaveSystem.git"
  },
  {
    "id": 39249488,
    "name": "HKSampleTrackingSystem",
    "full_name": "pfizer-commercial/HKSampleTrackingSystem",
    "clone_url": "https://github.com/pfizer-commercial/HKSampleTrackingSystem.git"
  },
  {
    "id": 39249515,
    "name": "HKTenderAndPricingSystem",
    "full_name": "pfizer-commercial/HKTenderAndPricingSystem",
    "clone_url": "https://github.com/pfizer-commercial/HKTenderAndPricingSystem.git"
  },
  {
    "id": 39250894,
    "name": "Arise",
    "full_name": "pfizer-commercial/Arise",
    "clone_url": "https://github.com/pfizer-commercial/Arise.git"
  },
  {
    "id": 39250904,
    "name": "AriseIcons",
    "full_name": "pfizer-commercial/AriseIcons",
    "clone_url": "https://github.com/pfizer-commercial/AriseIcons.git"
  },
  {
    "id": 39250909,
    "name": "AriseSampleApplication",
    "full_name": "pfizer-commercial/AriseSampleApplication",
    "clone_url": "https://github.com/pfizer-commercial/AriseSampleApplication.git"
  },
  {
    "id": 39250921,
    "name": "AriseWebsite",
    "full_name": "pfizer-commercial/AriseWebsite",
    "clone_url": "https://github.com/pfizer-commercial/AriseWebsite.git"
  },
  {
    "id": 39250931,
    "name": "AriseWebsiteTemplate",
    "full_name": "pfizer-commercial/AriseWebsiteTemplate",
    "clone_url": "https://github.com/pfizer-commercial/AriseWebsiteTemplate.git"
  },
  {
    "id": 39761917,
    "name": "ANAS",
    "full_name": "pfizer-commercial/ANAS",
    "clone_url": "https://github.com/pfizer-commercial/ANAS.git"
  },
  {
    "id": 39762219,
    "name": "iAssistant",
    "full_name": "pfizer-commercial/iAssistant",
    "clone_url": "https://github.com/pfizer-commercial/iAssistant.git"
  },
  {
    "id": 39762257,
    "name": "Spider",
    "full_name": "pfizer-commercial/Spider",
    "clone_url": "https://github.com/pfizer-commercial/Spider.git"
  },
  {
    "id": 39762266,
    "name": "MDE",
    "full_name": "pfizer-commercial/MDE",
    "clone_url": "https://github.com/pfizer-commercial/MDE.git"
  },
  {
    "id": 39771259,
    "name": "DEP",
    "full_name": "pfizer-commercial/DEP",
    "clone_url": "https://github.com/pfizer-commercial/DEP.git"
  },
  {
    "id": 39771813,
    "name": "MeetingRoomReservation",
    "full_name": "pfizer-commercial/MeetingRoomReservation",
    "clone_url": "https://github.com/pfizer-commercial/MeetingRoomReservation.git"
  },
  {
    "id": 39772342,
    "name": "RAS",
    "full_name": "pfizer-commercial/RAS",
    "clone_url": "https://github.com/pfizer-commercial/RAS.git"
  },
  {
    "id": 39772428,
    "name": "SMS",
    "full_name": "pfizer-commercial/SMS",
    "clone_url": "https://github.com/pfizer-commercial/SMS.git"
  },
  {
    "id": 39772457,
    "name": "TNT",
    "full_name": "pfizer-commercial/TNT",
    "clone_url": "https://github.com/pfizer-commercial/TNT.git"
  },
  {
    "id": 39772468,
    "name": "VeevaIF",
    "full_name": "pfizer-commercial/VeevaIF",
    "clone_url": "https://github.com/pfizer-commercial/VeevaIF.git"
  },
  {
    "id": 39772513,
    "name": "ChinaHcp",
    "full_name": "pfizer-commercial/ChinaHcp",
    "clone_url": "https://github.com/pfizer-commercial/ChinaHcp.git"
  },
  {
    "id": 41286399,
    "name": "SupplyMeChina",
    "full_name": "pfizer-commercial/SupplyMeChina",
    "clone_url": "https://github.com/pfizer-commercial/SupplyMeChina.git"
  },
  {
    "id": 84932663,
    "name": "ChinaDigitalHub",
    "full_name": "pfizer-commercial/ChinaDigitalHub",
    "clone_url": "https://github.com/pfizer-commercial/ChinaDigitalHub.git"
  },
  {
    "id": 271190248,
    "name": "ChinaBidding",
    "full_name": "pfizer-commercial/ChinaBidding",
    "clone_url": "https://github.com/pfizer-commercial/ChinaBidding.git"
  },
  {
    "id": 403813228,
    "name": "ChinaAutomationTool",
    "full_name": "pfizer-commercial/ChinaAutomationTool",
    "clone_url": "https://github.com/pfizer-commercial/ChinaAutomationTool.git"
  },
  {
    "id": 452919291,
    "name": "PfizerWeChat",
    "full_name": "pfizer-commercial/PfizerWeChat",
    "clone_url": "https://github.com/pfizer-commercial/PfizerWeChat.git"
  },
  {
    "id": 878234650,
    "name": "BACKUP-CHINA",
    "full_name": "pfizer-commercial/BACKUP-CHINA",
    "clone_url": "https://github.com/pfizer-commercial/BACKUP-CHINA.git"
  },
  {
    "id": 879816215,
    "name": ".github-private",
    "full_name": "pfizer-commercial/.github-private",
    "clone_url": "https://github.com/pfizer-commercial/.github-private.git"
  },
  {
    "id": 951230104,
    "name": "comm-chn-dep-ng",
    "full_name": "pfizer-commercial/comm-chn-dep-ng",
    "clone_url": "https://github.com/pfizer-commercial/comm-chn-dep-ng.git"
  },
  {
    "id": 982784288,
    "name": "comm-chn-VirtualMeeting",
    "full_name": "pfizer-commercial/comm-chn-VirtualMeeting",
    "clone_url": "https://github.com/pfizer-commercial/comm-chn-VirtualMeeting.git"
  }
]